json_cpp2_core.cpython-310-x86_64-linux-gnu.so
json_cpp2-0.0.111.dist-info/METADATA
json_cpp2-0.0.111.dist-info/WHEEL
json_cpp2-0.0.111.dist-info/top_level.txt
json_cpp2-0.0.111.dist-info/RECORD
json_cpp2/json_list.py
json_cpp2/json_parsable.py
json_cpp2/json_parser.py
json_cpp2/json_object.py
json_cpp2/__init__.py
