Metadata-Version: 2.1
Name: json-cpp2
Version: 0.0.111
Summary: A better json library
Author: German Espinosa
Author-email: germanespinosa@gmail.com
Requires: requests
Requires-Python: >=3.6
